{
    "version": 11,
    "id": "oH3Lgss59",
    "mapWidth": 21,
    "mapHeight": 19,
    "usernames": [
        "TA-linkoel",
        "MeltedToast"
    ],
    "stars": [
        0,
        74
    ],
    "cities": [
        98,
        307,
        308,
        337,
        220,
        105,
        222,
        190,
        340,
        10,
        248
    ],
    "cityArmies": [
        45,
        45,
        49,
        41,
        44,
        41,
        41,
        42,
        41,
        48,
        48
    ],
    "generals": [
        356,
        39
    ],
    "mountains": [
        12,
        13,
        20,
        27,
        33,
        45,
        46,
        49,
        50,
        53,
        66,
        71,
        76,
        86,
        92,
        107,
        108,
        115,
        117,
        122,
        124,
        126,
        128,
        136,
        137,
        139,
        143,
        149,
        152,
        154,
        156,
        160,
        163,
        166,
        168,
        171,
        177,
        180,
        187,
        192,
        197,
        200,
        205,
        206,
        209,
        214,
        217,
        218,
        219,
        221,
        223,
        229,
        231,
        233,
        235,
        239,
        243,
        245,
        246,
        247,
        256,
        259,
        260,
        268,
        269,
        275,
        278,
        289,
        294,
        311,
        317,
        320,
        334,
        339,
        341,
        347,
        351,
        362,
        365,
        367,
        374,
        377,
        391,
        395
    ],
    "moves": [
        {
            "index": 0,
            "start": 356,
            "end": 355,
            "is50": 0,
            "turn": 20
        },
        {
            "index": 0,
            "start": 355,
            "end": 354,
            "is50": 0,
            "turn": 21
        },
        {
            "index": 0,
            "start": 354,
            "end": 333,
            "is50": 0,
            "turn": 22
        },
        {
            "index": 0,
            "start": 333,
            "end": 332,
            "is50": 0,
            "turn": 23
        },
        {
            "index": 0,
            "start": 332,
            "end": 331,
            "is50": 0,
            "turn": 24
        },
        {
            "index": 1,
            "start": 39,
            "end": 60,
            "is50": 0,
            "turn": 24
        },
        {
            "index": 1,
            "start": 60,
            "end": 59,
            "is50": 0,
            "turn": 25
        },
        {
            "index": 0,
            "start": 331,
            "end": 330,
            "is50": 0,
            "turn": 25
        },
        {
            "index": 0,
            "start": 330,
            "end": 329,
            "is50": 0,
            "turn": 26
        },
        {
            "index": 1,
            "start": 59,
            "end": 58,
            "is50": 0,
            "turn": 26
        },
        {
            "index": 1,
            "start": 58,
            "end": 57,
            "is50": 0,
            "turn": 27
        },
        {
            "index": 0,
            "start": 329,
            "end": 328,
            "is50": 0,
            "turn": 27
        },
        {
            "index": 0,
            "start": 328,
            "end": 327,
            "is50": 0,
            "turn": 28
        },
        {
            "index": 1,
            "start": 57,
            "end": 56,
            "is50": 0,
            "turn": 28
        },
        {
            "index": 1,
            "start": 56,
            "end": 55,
            "is50": 0,
            "turn": 29
        },
        {
            "index": 0,
            "start": 327,
            "end": 306,
            "is50": 0,
            "turn": 29
        },
        {
            "index": 0,
            "start": 356,
            "end": 355,
            "is50": 0,
            "turn": 30
        },
        {
            "index": 1,
            "start": 55,
            "end": 54,
            "is50": 0,
            "turn": 30
        },
        {
            "index": 1,
            "start": 54,
            "end": 75,
            "is50": 0,
            "turn": 31
        },
        {
            "index": 0,
            "start": 355,
            "end": 354,
            "is50": 0,
            "turn": 31
        },
        {
            "index": 0,
            "start": 354,
            "end": 333,
            "is50": 0,
            "turn": 32
        },
        {
            "index": 1,
            "start": 75,
            "end": 74,
            "is50": 0,
            "turn": 32
        },
        {
            "index": 1,
            "start": 74,
            "end": 73,
            "is50": 0,
            "turn": 33
        },
        {
            "index": 0,
            "start": 333,
            "end": 312,
            "is50": 0,
            "turn": 33
        },
        {
            "index": 0,
            "start": 312,
            "end": 291,
            "is50": 0,
            "turn": 34
        },
        {
            "index": 1,
            "start": 73,
            "end": 72,
            "is50": 0,
            "turn": 34
        },
        {
            "index": 1,
            "start": 72,
            "end": 93,
            "is50": 0,
            "turn": 35
        },
        {
            "index": 0,
            "start": 291,
            "end": 270,
            "is50": 0,
            "turn": 35
        },
        {
            "index": 0,
            "start": 270,
            "end": 249,
            "is50": 0,
            "turn": 36
        },
        {
            "index": 1,
            "start": 39,
            "end": 60,
            "is50": 0,
            "turn": 36
        },
        {
            "index": 1,
            "start": 60,
            "end": 81,
            "is50": 0,
            "turn": 37
        },
        {
            "index": 0,
            "start": 249,
            "end": 228,
            "is50": 0,
            "turn": 37
        },
        {
            "index": 0,
            "start": 356,
            "end": 355,
            "is50": 0,
            "turn": 38
        },
        {
            "index": 1,
            "start": 81,
            "end": 102,
            "is50": 0,
            "turn": 38
        },
        {
            "index": 1,
            "start": 102,
            "end": 123,
            "is50": 0,
            "turn": 39
        },
        {
            "index": 0,
            "start": 355,
            "end": 354,
            "is50": 0,
            "turn": 39
        },
        {
            "index": 0,
            "start": 354,
            "end": 353,
            "is50": 0,
            "turn": 40
        },
        {
            "index": 1,
            "start": 123,
            "end": 144,
            "is50": 0,
            "turn": 40
        },
        {
            "index": 1,
            "start": 144,
            "end": 165,
            "is50": 0,
            "turn": 41
        },
        {
            "index": 0,
            "start": 353,
            "end": 352,
            "is50": 0,
            "turn": 41
        },
        {
            "index": 0,
            "start": 352,
            "end": 373,
            "is50": 0,
            "turn": 42
        },
        {
            "index": 1,
            "start": 165,
            "end": 186,
            "is50": 0,
            "turn": 42
        },
        {
            "index": 0,
            "start": 373,
            "end": 372,
            "is50": 0,
            "turn": 43
        },
        {
            "index": 0,
            "start": 356,
            "end": 355,
            "is50": 0,
            "turn": 44
        },
        {
            "index": 1,
            "start": 39,
            "end": 40,
            "is50": 0,
            "turn": 44
        },
        {
            "index": 1,
            "start": 40,
            "end": 41,
            "is50": 0,
            "turn": 45
        },
        {
            "index": 0,
            "start": 355,
            "end": 376,
            "is50": 0,
            "turn": 45
        },
        {
            "index": 0,
            "start": 376,
            "end": 397,
            "is50": 0,
            "turn": 46
        },
        {
            "index": 1,
            "start": 41,
            "end": 62,
            "is50": 0,
            "turn": 46
        },
        {
            "index": 1,
            "start": 62,
            "end": 83,
            "is50": 0,
            "turn": 47
        },
        {
            "index": 0,
            "start": 397,
            "end": 398,
            "is50": 0,
            "turn": 47
        },
        {
            "index": 0,
            "start": 356,
            "end": 335,
            "is50": 0,
            "turn": 48
        },
        {
            "index": 1,
            "start": 39,
            "end": 18,
            "is50": 0,
            "turn": 48
        },
        {
            "index": 1,
            "start": 18,
            "end": 19,
            "is50": 0,
            "turn": 49
        },
        {
            "index": 0,
            "start": 335,
            "end": 314,
            "is50": 0,
            "turn": 49
        },
        {
            "index": 0,
            "start": 398,
            "end": 397,
            "is50": 0,
            "turn": 50
        },
        {
            "index": 1,
            "start": 19,
            "end": 18,
            "is50": 0,
            "turn": 50
        },
        {
            "index": 1,
            "start": 18,
            "end": 39,
            "is50": 0,
            "turn": 51
        },
        {
            "index": 0,
            "start": 397,
            "end": 376,
            "is50": 0,
            "turn": 51
        },
        {
            "index": 0,
            "start": 376,
            "end": 355,
            "is50": 0,
            "turn": 52
        },
        {
            "index": 1,
            "start": 83,
            "end": 62,
            "is50": 0,
            "turn": 52
        },
        {
            "index": 1,
            "start": 62,
            "end": 41,
            "is50": 0,
            "turn": 53
        },
        {
            "index": 0,
            "start": 373,
            "end": 372,
            "is50": 0,
            "turn": 53
        },
        {
            "index": 0,
            "start": 372,
            "end": 371,
            "is50": 0,
            "turn": 54
        },
        {
            "index": 1,
            "start": 41,
            "end": 40,
            "is50": 0,
            "turn": 54
        },
        {
            "index": 1,
            "start": 40,
            "end": 39,
            "is50": 0,
            "turn": 55
        },
        {
            "index": 0,
            "start": 371,
            "end": 370,
            "is50": 0,
            "turn": 55
        },
        {
            "index": 0,
            "start": 352,
            "end": 353,
            "is50": 0,
            "turn": 56
        },
        {
            "index": 1,
            "start": 186,
            "end": 165,
            "is50": 0,
            "turn": 56
        },
        {
            "index": 1,
            "start": 165,
            "end": 144,
            "is50": 0,
            "turn": 57
        },
        {
            "index": 0,
            "start": 353,
            "end": 354,
            "is50": 0,
            "turn": 57
        },
        {
            "index": 0,
            "start": 329,
            "end": 328,
            "is50": 0,
            "turn": 58
        },
        {
            "index": 1,
            "start": 144,
            "end": 123,
            "is50": 0,
            "turn": 58
        },
        {
            "index": 1,
            "start": 123,
            "end": 102,
            "is50": 0,
            "turn": 59
        },
        {
            "index": 0,
            "start": 328,
            "end": 327,
            "is50": 0,
            "turn": 59
        },
        {
            "index": 0,
            "start": 327,
            "end": 306,
            "is50": 0,
            "turn": 60
        },
        {
            "index": 1,
            "start": 102,
            "end": 81,
            "is50": 0,
            "turn": 60
        },
        {
            "index": 1,
            "start": 81,
            "end": 60,
            "is50": 0,
            "turn": 61
        },
        {
            "index": 0,
            "start": 306,
            "end": 305,
            "is50": 0,
            "turn": 61
        },
        {
            "index": 0,
            "start": 305,
            "end": 304,
            "is50": 0,
            "turn": 62
        },
        {
            "index": 1,
            "start": 39,
            "end": 60,
            "is50": 0,
            "turn": 62
        },
        {
            "index": 1,
            "start": 60,
            "end": 59,
            "is50": 0,
            "turn": 63
        },
        {
            "index": 0,
            "start": 304,
            "end": 303,
            "is50": 0,
            "turn": 63
        },
        {
            "index": 0,
            "start": 303,
            "end": 282,
            "is50": 0,
            "turn": 64
        },
        {
            "index": 1,
            "start": 59,
            "end": 58,
            "is50": 0,
            "turn": 64
        },
        {
            "index": 1,
            "start": 58,
            "end": 57,
            "is50": 0,
            "turn": 65
        },
        {
            "index": 0,
            "start": 330,
            "end": 331,
            "is50": 0,
            "turn": 65
        },
        {
            "index": 0,
            "start": 331,
            "end": 332,
            "is50": 0,
            "turn": 66
        },
        {
            "index": 1,
            "start": 57,
            "end": 56,
            "is50": 0,
            "turn": 66
        },
        {
            "index": 1,
            "start": 56,
            "end": 55,
            "is50": 0,
            "turn": 67
        },
        {
            "index": 0,
            "start": 332,
            "end": 333,
            "is50": 0,
            "turn": 67
        },
        {
            "index": 0,
            "start": 314,
            "end": 335,
            "is50": 0,
            "turn": 68
        },
        {
            "index": 1,
            "start": 55,
            "end": 54,
            "is50": 0,
            "turn": 68
        },
        {
            "index": 1,
            "start": 54,
            "end": 75,
            "is50": 0,
            "turn": 69
        },
        {
            "index": 0,
            "start": 335,
            "end": 356,
            "is50": 0,
            "turn": 69
        },
        {
            "index": 0,
            "start": 356,
            "end": 355,
            "is50": 0,
            "turn": 70
        },
        {
            "index": 1,
            "start": 75,
            "end": 74,
            "is50": 0,
            "turn": 70
        },
        {
            "index": 1,
            "start": 74,
            "end": 73,
            "is50": 0,
            "turn": 71
        },
        {
            "index": 0,
            "start": 355,
            "end": 354,
            "is50": 0,
            "turn": 71
        },
        {
            "index": 0,
            "start": 354,
            "end": 333,
            "is50": 0,
            "turn": 72
        },
        {
            "index": 1,
            "start": 73,
            "end": 72,
            "is50": 0,
            "turn": 72
        },
        {
            "index": 1,
            "start": 72,
            "end": 93,
            "is50": 0,
            "turn": 73
        },
        {
            "index": 0,
            "start": 333,
            "end": 312,
            "is50": 0,
            "turn": 73
        },
        {
            "index": 0,
            "start": 312,
            "end": 291,
            "is50": 0,
            "turn": 74
        },
        {
            "index": 1,
            "start": 93,
            "end": 114,
            "is50": 0,
            "turn": 74
        },
        {
            "index": 1,
            "start": 114,
            "end": 113,
            "is50": 0,
            "turn": 75
        },
        {
            "index": 0,
            "start": 291,
            "end": 270,
            "is50": 0,
            "turn": 75
        },
        {
            "index": 0,
            "start": 270,
            "end": 249,
            "is50": 0,
            "turn": 76
        },
        {
            "index": 1,
            "start": 113,
            "end": 112,
            "is50": 0,
            "turn": 76
        },
        {
            "index": 1,
            "start": 112,
            "end": 111,
            "is50": 0,
            "turn": 77
        },
        {
            "index": 0,
            "start": 249,
            "end": 228,
            "is50": 0,
            "turn": 77
        },
        {
            "index": 0,
            "start": 228,
            "end": 227,
            "is50": 0,
            "turn": 78
        },
        {
            "index": 1,
            "start": 111,
            "end": 132,
            "is50": 0,
            "turn": 78
        },
        {
            "index": 1,
            "start": 132,
            "end": 153,
            "is50": 0,
            "turn": 79
        },
        {
            "index": 0,
            "start": 227,
            "end": 226,
            "is50": 0,
            "turn": 79
        },
        {
            "index": 0,
            "start": 226,
            "end": 225,
            "is50": 0,
            "turn": 80
        },
        {
            "index": 1,
            "start": 153,
            "end": 174,
            "is50": 0,
            "turn": 80
        },
        {
            "index": 1,
            "start": 174,
            "end": 195,
            "is50": 0,
            "turn": 81
        },
        {
            "index": 0,
            "start": 225,
            "end": 204,
            "is50": 0,
            "turn": 81
        },
        {
            "index": 0,
            "start": 204,
            "end": 183,
            "is50": 0,
            "turn": 82
        },
        {
            "index": 1,
            "start": 195,
            "end": 216,
            "is50": 0,
            "turn": 82
        },
        {
            "index": 1,
            "start": 216,
            "end": 237,
            "is50": 0,
            "turn": 83
        },
        {
            "index": 0,
            "start": 183,
            "end": 162,
            "is50": 0,
            "turn": 83
        },
        {
            "index": 0,
            "start": 162,
            "end": 141,
            "is50": 0,
            "turn": 84
        },
        {
            "index": 1,
            "start": 237,
            "end": 258,
            "is50": 0,
            "turn": 84
        },
        {
            "index": 1,
            "start": 258,
            "end": 279,
            "is50": 0,
            "turn": 85
        },
        {
            "index": 0,
            "start": 141,
            "end": 142,
            "is50": 0,
            "turn": 85
        },
        {
            "index": 0,
            "start": 142,
            "end": 121,
            "is50": 0,
            "turn": 86
        },
        {
            "index": 1,
            "start": 279,
            "end": 300,
            "is50": 0,
            "turn": 86
        },
        {
            "index": 1,
            "start": 300,
            "end": 321,
            "is50": 0,
            "turn": 87
        },
        {
            "index": 0,
            "start": 121,
            "end": 100,
            "is50": 0,
            "turn": 87
        },
        {
            "index": 0,
            "start": 100,
            "end": 79,
            "is50": 0,
            "turn": 88
        },
        {
            "index": 1,
            "start": 321,
            "end": 342,
            "is50": 0,
            "turn": 88
        },
        {
            "index": 1,
            "start": 342,
            "end": 363,
            "is50": 0,
            "turn": 89
        },
        {
            "index": 0,
            "start": 79,
            "end": 58,
            "is50": 0,
            "turn": 89
        },
        {
            "index": 0,
            "start": 58,
            "end": 57,
            "is50": 0,
            "turn": 90
        },
        {
            "index": 1,
            "start": 363,
            "end": 384,
            "is50": 0,
            "turn": 90
        },
        {
            "index": 1,
            "start": 384,
            "end": 385,
            "is50": 0,
            "turn": 91
        },
        {
            "index": 0,
            "start": 57,
            "end": 56,
            "is50": 0,
            "turn": 91
        },
        {
            "index": 0,
            "start": 56,
            "end": 55,
            "is50": 0,
            "turn": 92
        },
        {
            "index": 1,
            "start": 385,
            "end": 386,
            "is50": 0,
            "turn": 92
        },
        {
            "index": 1,
            "start": 386,
            "end": 387,
            "is50": 0,
            "turn": 93
        },
        {
            "index": 0,
            "start": 55,
            "end": 54,
            "is50": 0,
            "turn": 93
        },
        {
            "index": 0,
            "start": 54,
            "end": 75,
            "is50": 0,
            "turn": 94
        },
        {
            "index": 1,
            "start": 387,
            "end": 388,
            "is50": 0,
            "turn": 94
        },
        {
            "index": 1,
            "start": 388,
            "end": 389,
            "is50": 0,
            "turn": 95
        },
        {
            "index": 0,
            "start": 75,
            "end": 74,
            "is50": 0,
            "turn": 95
        },
        {
            "index": 0,
            "start": 74,
            "end": 73,
            "is50": 0,
            "turn": 96
        },
        {
            "index": 1,
            "start": 389,
            "end": 390,
            "is50": 0,
            "turn": 96
        },
        {
            "index": 1,
            "start": 390,
            "end": 369,
            "is50": 0,
            "turn": 97
        },
        {
            "index": 0,
            "start": 73,
            "end": 94,
            "is50": 0,
            "turn": 97
        },
        {
            "index": 0,
            "start": 94,
            "end": 93,
            "is50": 0,
            "turn": 98
        },
        {
            "index": 1,
            "start": 369,
            "end": 370,
            "is50": 0,
            "turn": 98
        },
        {
            "index": 1,
            "start": 370,
            "end": 371,
            "is50": 0,
            "turn": 99
        },
        {
            "index": 0,
            "start": 398,
            "end": 397,
            "is50": 0,
            "turn": 100
        },
        {
            "index": 1,
            "start": 384,
            "end": 383,
            "is50": 0,
            "turn": 101
        },
        {
            "index": 0,
            "start": 397,
            "end": 376,
            "is50": 0,
            "turn": 101
        },
        {
            "index": 0,
            "start": 376,
            "end": 355,
            "is50": 0,
            "turn": 102
        },
        {
            "index": 1,
            "start": 363,
            "end": 364,
            "is50": 0,
            "turn": 102
        },
        {
            "index": 1,
            "start": 342,
            "end": 343,
            "is50": 0,
            "turn": 103
        },
        {
            "index": 0,
            "start": 314,
            "end": 335,
            "is50": 0,
            "turn": 103
        },
        {
            "index": 0,
            "start": 335,
            "end": 356,
            "is50": 0,
            "turn": 104
        },
        {
            "index": 1,
            "start": 321,
            "end": 322,
            "is50": 0,
            "turn": 104
        },
        {
            "index": 1,
            "start": 300,
            "end": 301,
            "is50": 0,
            "turn": 105
        },
        {
            "index": 0,
            "start": 327,
            "end": 328,
            "is50": 0,
            "turn": 105
        },
        {
            "index": 0,
            "start": 328,
            "end": 329,
            "is50": 0,
            "turn": 106
        },
        {
            "index": 1,
            "start": 279,
            "end": 280,
            "is50": 0,
            "turn": 106
        },
        {
            "index": 1,
            "start": 258,
            "end": 257,
            "is50": 0,
            "turn": 107
        },
        {
            "index": 0,
            "start": 329,
            "end": 330,
            "is50": 0,
            "turn": 107
        },
        {
            "index": 0,
            "start": 330,
            "end": 331,
            "is50": 0,
            "turn": 108
        },
        {
            "index": 1,
            "start": 237,
            "end": 238,
            "is50": 0,
            "turn": 108
        },
        {
            "index": 1,
            "start": 216,
            "end": 215,
            "is50": 0,
            "turn": 109
        },
        {
            "index": 0,
            "start": 331,
            "end": 352,
            "is50": 0,
            "turn": 109
        },
        {
            "index": 0,
            "start": 352,
            "end": 353,
            "is50": 0,
            "turn": 110
        },
        {
            "index": 1,
            "start": 195,
            "end": 196,
            "is50": 0,
            "turn": 110
        },
        {
            "index": 1,
            "start": 174,
            "end": 173,
            "is50": 0,
            "turn": 111
        },
        {
            "index": 0,
            "start": 332,
            "end": 353,
            "is50": 0,
            "turn": 111
        },
        {
            "index": 0,
            "start": 353,
            "end": 354,
            "is50": 0,
            "turn": 112
        },
        {
            "index": 1,
            "start": 153,
            "end": 132,
            "is50": 0,
            "turn": 112
        },
        {
            "index": 1,
            "start": 132,
            "end": 131,
            "is50": 0,
            "turn": 113
        },
        {
            "index": 0,
            "start": 306,
            "end": 285,
            "is50": 0,
            "turn": 113
        },
        {
            "index": 0,
            "start": 305,
            "end": 284,
            "is50": 0,
            "turn": 114
        },
        {
            "index": 1,
            "start": 131,
            "end": 130,
            "is50": 0,
            "turn": 114
        },
        {
            "index": 1,
            "start": 111,
            "end": 90,
            "is50": 0,
            "turn": 115
        },
        {
            "index": 0,
            "start": 304,
            "end": 325,
            "is50": 0,
            "turn": 115
        },
        {
            "index": 0,
            "start": 303,
            "end": 324,
            "is50": 0,
            "turn": 116
        },
        {
            "index": 1,
            "start": 112,
            "end": 91,
            "is50": 0,
            "turn": 116
        },
        {
            "index": 1,
            "start": 19,
            "end": 18,
            "is50": 0,
            "turn": 117
        },
        {
            "index": 0,
            "start": 282,
            "end": 261,
            "is50": 0,
            "turn": 117
        },
        {
            "index": 0,
            "start": 356,
            "end": 355,
            "is50": 0,
            "turn": 118
        },
        {
            "index": 1,
            "start": 18,
            "end": 39,
            "is50": 0,
            "turn": 118
        },
        {
            "index": 1,
            "start": 83,
            "end": 104,
            "is50": 0,
            "turn": 119
        },
        {
            "index": 0,
            "start": 355,
            "end": 354,
            "is50": 0,
            "turn": 119
        },
        {
            "index": 0,
            "start": 354,
            "end": 333,
            "is50": 0,
            "turn": 120
        },
        {
            "index": 1,
            "start": 62,
            "end": 61,
            "is50": 0,
            "turn": 120
        },
        {
            "index": 1,
            "start": 41,
            "end": 40,
            "is50": 0,
            "turn": 121
        },
        {
            "index": 0,
            "start": 333,
            "end": 312,
            "is50": 0,
            "turn": 121
        },
        {
            "index": 0,
            "start": 312,
            "end": 291,
            "is50": 0,
            "turn": 122
        },
        {
            "index": 1,
            "start": 40,
            "end": 39,
            "is50": 0,
            "turn": 122
        },
        {
            "index": 1,
            "start": 370,
            "end": 371,
            "is50": 0,
            "turn": 123
        },
        {
            "index": 0,
            "start": 291,
            "end": 270,
            "is50": 0,
            "turn": 123
        },
        {
            "index": 0,
            "start": 270,
            "end": 249,
            "is50": 0,
            "turn": 124
        },
        {
            "index": 1,
            "start": 371,
            "end": 372,
            "is50": 0,
            "turn": 124
        },
        {
            "index": 1,
            "start": 372,
            "end": 373,
            "is50": 0,
            "turn": 125
        },
        {
            "index": 0,
            "start": 249,
            "end": 228,
            "is50": 0,
            "turn": 125
        },
        {
            "index": 0,
            "start": 228,
            "end": 227,
            "is50": 0,
            "turn": 126
        },
        {
            "index": 1,
            "start": 369,
            "end": 348,
            "is50": 0,
            "turn": 126
        },
        {
            "index": 1,
            "start": 389,
            "end": 368,
            "is50": 0,
            "turn": 127
        },
        {
            "index": 0,
            "start": 227,
            "end": 226,
            "is50": 0,
            "turn": 127
        },
        {
            "index": 0,
            "start": 226,
            "end": 225,
            "is50": 0,
            "turn": 128
        },
        {
            "index": 1,
            "start": 39,
            "end": 60,
            "is50": 0,
            "turn": 128
        },
        {
            "index": 1,
            "start": 60,
            "end": 81,
            "is50": 0,
            "turn": 129
        },
        {
            "index": 0,
            "start": 225,
            "end": 204,
            "is50": 0,
            "turn": 129
        },
        {
            "index": 0,
            "start": 204,
            "end": 183,
            "is50": 0,
            "turn": 130
        },
        {
            "index": 1,
            "start": 81,
            "end": 102,
            "is50": 0,
            "turn": 130
        },
        {
            "index": 1,
            "start": 102,
            "end": 123,
            "is50": 0,
            "turn": 131
        },
        {
            "index": 0,
            "start": 183,
            "end": 162,
            "is50": 0,
            "turn": 131
        },
        {
            "index": 0,
            "start": 162,
            "end": 141,
            "is50": 0,
            "turn": 132
        },
        {
            "index": 1,
            "start": 123,
            "end": 144,
            "is50": 0,
            "turn": 132
        },
        {
            "index": 1,
            "start": 144,
            "end": 165,
            "is50": 0,
            "turn": 133
        },
        {
            "index": 0,
            "start": 141,
            "end": 142,
            "is50": 0,
            "turn": 133
        },
        {
            "index": 0,
            "start": 142,
            "end": 121,
            "is50": 0,
            "turn": 134
        },
        {
            "index": 1,
            "start": 165,
            "end": 186,
            "is50": 0,
            "turn": 134
        },
        {
            "index": 1,
            "start": 186,
            "end": 207,
            "is50": 0,
            "turn": 135
        },
        {
            "index": 0,
            "start": 121,
            "end": 100,
            "is50": 0,
            "turn": 135
        },
        {
            "index": 0,
            "start": 100,
            "end": 79,
            "is50": 0,
            "turn": 136
        },
        {
            "index": 1,
            "start": 207,
            "end": 228,
            "is50": 0,
            "turn": 136
        },
        {
            "index": 1,
            "start": 228,
            "end": 249,
            "is50": 0,
            "turn": 137
        },
        {
            "index": 0,
            "start": 79,
            "end": 58,
            "is50": 0,
            "turn": 137
        },
        {
            "index": 0,
            "start": 58,
            "end": 59,
            "is50": 0,
            "turn": 138
        },
        {
            "index": 1,
            "start": 249,
            "end": 270,
            "is50": 0,
            "turn": 138
        },
        {
            "index": 1,
            "start": 270,
            "end": 291,
            "is50": 0,
            "turn": 139
        },
        {
            "index": 0,
            "start": 59,
            "end": 60,
            "is50": 0,
            "turn": 139
        },
        {
            "index": 0,
            "start": 60,
            "end": 39,
            "is50": 0,
            "turn": 140
        }
    ],
    "afks": [],
    "teams": [
        1,
        2
    ],
    "map": null,
    "neutrals": [],
    "neutralArmies": [],
    "swamps": [],
    "chat": [
        {
            "text": "gl hf",
            "prefix": "",
            "playerIndex": 1,
            "turn": 8
        },
        {
            "text": "gl hf",
            "prefix": "",
            "playerIndex": 0,
            "turn": 12
        }
    ],
    "playerColors": [
        0,
        1
    ],
    "lights": [],
    "speed": 1,
    "city_density": 0.5,
    "mountain_density": 0.5,
    "swamp_density": 0,
    "modifiers": [],
    "observatories": [],
    "lookouts": [],
    "deserts": [],
    "city_fairness": -1,
    "spawn_fairness": -1,
    "desert_density": 0,
    "lookout_density": 0,
    "observatory_density": 0
}